bin/__init__.py
bin/rouge_cmd.py
rouge/__init__.py
rouge/rouge.py
rouge/rouge_score.py
rouge_chinese/__init__.py
rouge_chinese/rouge.py
rouge_chinese/rouge_score.py
rouge_chinese-1.0.3.dist-info/LICENSE
rouge_chinese-1.0.3.dist-info/METADATA
rouge_chinese-1.0.3.dist-info/WHEEL
rouge_chinese-1.0.3.dist-info/entry_points.txt
rouge_chinese-1.0.3.dist-info/top_level.txt
rouge_chinese-1.0.3.dist-info/RECORD
