Metadata-Version: 2.1
Name: rouge_chinese
Version: 1.0.3
Summary: Python ROUGE Score Implementation for Chinese Language Task (official rouge score)
Home-page: https://github.com/Isaac-JL-Chen/rouge_chinese.git
Author: Isaac-JL-Chen
Author-email: chn.jianlin@gmail.com
License: LICENCE.txt
Keywords: NL,CL,natural language processing,computational linguistics,summarization,chinese
Platform: UNKNOWN
Classifier: Intended Audience :: Science/Research
Classifier: Programming Language :: Python :: 3
Classifier: Topic :: Text Processing :: Linguistic
